flight_tracer/__init__.py
flight_tracer/core.py
tests/__init__.py
tests/test_core.py
flight_tracer-0.1.1.dist-info/METADATA
flight_tracer-0.1.1.dist-info/WHEEL
flight_tracer-0.1.1.dist-info/top_level.txt
flight_tracer-0.1.1.dist-info/RECORD
