Metadata-Version: 2.2
Name: flight_tracer
Version: 0.1.1
Summary: A package to fetch, process, store and plot aircraft trace data from ADS-B Exchange.
Home-page: https://github.com/stiles/flight_tracer
Author: Matt Stiles
Author-email: mattstiles@gmail.com
License: CC0-1.0
Classifier: Programming Language :: Python :: 3
Classifier: License :: CC0 1.0 Universal (CC0 1.0) Public Domain Dedication
Classifier: Operating System :: OS Independent
Requires-Python: >=3.7
Requires-Dist: requests
Requires-Dist: pandas
Requires-Dist: geopandas
Requires-Dist: boto3
Requires-Dist: matplotlib
Requires-Dist: contextily
Requires-Dist: shapely
Dynamic: author
Dynamic: author-email
Dynamic: classifier
Dynamic: description
Dynamic: description-content-type
Dynamic: home-page
Dynamic: license
Dynamic: requires-dist
Dynamic: requires-python
Dynamic: summary
